bluebox/__init__.py
bluebox/__main__.py
bluebox/box.py
bluebox/cli.py
bluebox/freqs.py
bluebox/wave.py
bluebox/backends/__init__.py
bluebox/backends/backend_dummy.py
bluebox/backends/backend_pyaudio.py
bluebox/backends/backend_wav.py
bluebox/backends/base.py
mfbluebox-0.2.2.dist-info/METADATA
mfbluebox-0.2.2.dist-info/WHEEL
mfbluebox-0.2.2.dist-info/licenses/LICENSE.md
mfbluebox-0.2.2.dist-info/RECORD
