Metadata-Version: 2.4
Name: mfbluebox
Version: 0.2.2
Summary: A python (Dual-Tone) Multi-Frequency (DTMF) tone generator.
Project-URL: Homepage, https://github.com/zeyus/Python3BlueBox
Project-URL: Bug Tracker, https://github.com/zeyus/Python3BlueBox/issues
Author-email: zeyus <support@zeyus.com>
License: MIT License
License-File: LICENSE.md
Classifier: License :: OSI Approved :: MIT License
Classifier: Operating System :: OS Independent
Classifier: Programming Language :: Python :: 3
Requires-Python: >=3.9
Requires-Dist: pyaudio>=0.2.14
Provides-Extra: dev
Requires-Dist: build>=1.2.2; extra == 'dev'
Requires-Dist: flake8>=7.3.0; extra == 'dev'
Requires-Dist: mypy>=1.15.0; extra == 'dev'
Requires-Dist: pytest>=8.3.5; extra == 'dev'
